setup.py
ooxcb/__init__.py
ooxcb/atoms.py
ooxcb/autotypes.py
ooxcb/conn.py
ooxcb/constant.py
ooxcb/cookie.py
ooxcb/eventsys.py
ooxcb/exception.py
ooxcb/ext.py
ooxcb/keysymdef.py
ooxcb/keysyms.py
ooxcb/libc.py
ooxcb/libxcb.py
ooxcb/list.py
ooxcb/memstream.py
ooxcb/protobj.py
ooxcb/resource.py
ooxcb/types.py
ooxcb/util.py
ooxcb.egg-info/PKG-INFO
ooxcb.egg-info/SOURCES.txt
ooxcb.egg-info/dependency_links.txt
ooxcb.egg-info/top_level.txt
ooxcb/contrib/__init__.py
ooxcb/contrib/cairo.py
ooxcb/contrib/cursors.py
ooxcb/contrib/ewmh.py
ooxcb/contrib/gdk.py
ooxcb/contrib/icccm.py
ooxcb/contrib/pil.py
ooxcb/contrib/sizehints.py
ooxcb/protocol/__init__.py
ooxcb/protocol/bigreq.py
ooxcb/protocol/composite.py
ooxcb/protocol/damage.py
ooxcb/protocol/record.py
ooxcb/protocol/render.py
ooxcb/protocol/screensaver.py
ooxcb/protocol/shape.py
ooxcb/protocol/xfixes.py
ooxcb/protocol/xproto.py
ooxcb/protocol/xtest.py