Metadata-Version: 1.0
Name: ooxcb
Version: 1.2
Summary: An object-oriented X Python Binding, based on xpyb
Home-page: http://samurai-x.org
Author: Friedrich Weber
Author-email: fred@reichbier.de
License: UNKNOWN
Download-URL: http://samurai-x.org/downloads/
Keywords: xcb cairo
Platform: UNKNOWN
